file_handler/__init__.py
file_handler/filer.py
mainApp/__init__.py
mainApp/miniAnsible.py
mainApp/serial_execution.py
roverApp-1.0.dist-info/METADATA
roverApp-1.0.dist-info/WHEEL
roverApp-1.0.dist-info/top_level.txt
roverApp-1.0.dist-info/RECORD
